esco_skill_extractor/__init__.py
esco_skill_extractor/__main__.py
esco_skill_extractor/data/occupations.csv
esco_skill_extractor/data/skills.csv
esco_skill_extractor/static/eu.webp
esco_skill_extractor/static/index.css
esco_skill_extractor/static/index.js
esco_skill_extractor/templates/index.html
esco_skill_extractor-0.1.18.dist-info/licenses/LICENSE
esco_skill_extractor-0.1.18.dist-info/METADATA
esco_skill_extractor-0.1.18.dist-info/WHEEL
esco_skill_extractor-0.1.18.dist-info/top_level.txt
esco_skill_extractor-0.1.18.dist-info/RECORD
