Metadata-Version: 2.4
Name: esco-skill-extractor
Version: 0.1.18
Summary: Extract ESCO skills from texts such as job descriptions or CVs
Home-page: https://github.com/KonstantinosPetrakis/esco-skill-extractor
Author: Konstantinos Petrakis
Author-email: konstpetrakis01@gmail.com
Classifier: Programming Language :: Python :: 3
Classifier: License :: OSI Approved :: MIT License
Classifier: Operating System :: OS Independent
License-File: LICENSE
Requires-Dist: sentence-transformers
Requires-Dist: Flask
Requires-Dist: pandas
Requires-Dist: waitress
Dynamic: author
Dynamic: author-email
Dynamic: classifier
Dynamic: description
Dynamic: description-content-type
Dynamic: home-page
Dynamic: license-file
Dynamic: requires-dist
Dynamic: summary
